{
  "version": "7",
  "dialect": "postgresql",
  "entries": [
    {
      "idx": 0,
      "version": "7",
      "when": 1758926666130,
      "tag": "0000_young_taskmaster",
      "breakpoints": true
    },
    {
      "idx": 1,
      "version": "7",
      "when": 1758982272516,
      "tag": "0001_bizarre_marrow",
      "breakpoints": true
    },
    {
      "idx": 2,
      "version": "7",
      "when": 1758982350613,
      "tag": "0002_magical_colonel_america",
      "breakpoints": true
    }
  ]
}